LICENSE.txt
MANIFEST.in
README.rst
setup.cfg
setup.py
list_printer_folder/__init__.py
list_printer_folder/list_printer_file.py
list_printer_package.egg-info/PKG-INFO
list_printer_package.egg-info/SOURCES.txt
list_printer_package.egg-info/dependency_links.txt
list_printer_package.egg-info/entry_points.txt
list_printer_package.egg-info/requires.txt
list_printer_package.egg-info/top_level.txt