Metadata-Version: 1.1
Name: list-printer-package
Version: 0.1
Summary: A module to print the contents of lists
Home-page: https://upload.pypi.org/legacy/
Author: Laura Hampton
Author-email: laura@laura-hampton.com
License: MIT
Keywords: sample list printer
Platform: UNKNOWN
Classifier: Development Status :: 3 - Alpha
Classifier: Intended Audience :: Developers
Classifier: Topic :: Software Development :: Build Tools
Classifier: License :: OSI Approved :: MIT License
Classifier: Programming Language :: Python :: 3.6
